Metadata-Version: 1.1
Name: morf-job-api
Version: 0.1.7
Summary: MORF Jobs package
Home-page: https://morf-pcla.education/
Author: Michael Mogessie
Author-email: pcla-morf@gse.upenn.edu
License: UNKNOWN
Keywords: python,morf
Platform: UNKNOWN
Classifier: Development Status :: 3 - Alpha
Classifier: Intended Audience :: Education
Classifier: Programming Language :: Python :: 2
Classifier: Operating System :: POSIX :: Linux
Classifier: Operating System :: MacOS :: MacOS X
Classifier: Operating System :: Microsoft :: Windows
